econsieve/__init__.py
econsieve/kalman_filter.py
econsieve/npas.py
econsieve/sigma_points.py
econsieve/stats.py
econsieve/tenkf.py
econsieve/ukf.py
econsieve-0.0.9.dist-info/LICENSE
econsieve-0.0.9.dist-info/METADATA
econsieve-0.0.9.dist-info/WHEEL
econsieve-0.0.9.dist-info/top_level.txt
econsieve-0.0.9.dist-info/RECORD
