Metadata-Version: 2.1
Name: econsieve
Version: 0.0.9
Summary: Linear and nonlinear Bayesian filters
Home-page: https://github.com/gboehl/econsieve
Author: Gregor Boehl
Author-email: admin@gregorboehl.com
License: MIT
Classifier: License :: OSI Approved :: MIT License
Classifier: Programming Language :: Python :: 3
Classifier: Programming Language :: Python :: 3.9
License-File: LICENSE
Requires-Dist: matplotlib
Requires-Dist: scipy
Requires-Dist: numpy
Requires-Dist: numba
Requires-Dist: grgrlib >=0.1.13
